CHANGELOG.md
LICENSE.txt
MANIFEST.in
README.md
pyproject.toml
setup.py
cyprecice/Participant.pxd
cyprecice/cyprecice.cpp
cyprecice/cyprecice.pxd
cyprecice/cyprecice.pyx
precice/__init__.py
pyprecice.egg-info/PKG-INFO
pyprecice.egg-info/SOURCES.txt
pyprecice.egg-info/dependency_links.txt
pyprecice.egg-info/requires.txt
pyprecice.egg-info/top_level.txt
test/Participant.cpp
test/test_bindings_module.py