Metadata-Version: 2.4
Name: pyprecice
Version: 3.3.1
Summary: Python language bindings for the preCICE coupling library
Author-email: the preCICE developers <info@precice.org>
License-Expression: LGPL-3.0
Project-URL: changelog, https://github.com/precice/python-bindings/blob/develop/CHANGELOG.md
Project-URL: documentation, https://precice.org/installation-bindings-python.html
Project-URL: homepage, https://precice.org
Project-URL: issues, https://github.com/precice/python-bindings/issues
Project-URL: repository, https://github.com/precice/python-bindings.git
Project-URL: sponsor, https://precice.org/community-support-precice.html
Requires-Python: >=3.10
License-File: LICENSE.txt
Requires-Dist: numpy
Requires-Dist: mpi4py
Dynamic: license-file
